{"name":"Jgridder","tagline":"UI component that fits elements in a sized html grid","body":"#JGRIDDER\r\n\r\n## Pitch\r\n\r\njgridder is a UI javascript component that fits a number of elements in a sized html grid. It uses jQuery. \r\n\r\n## Demo\r\n<http://eloone.net/jgridder/demo/>\r\n\r\n## Requirements\r\nTo get this script working include the following in your webpage :\r\n\r\nThe javascript files :\r\n\r\n `<script src=\"http://code.jquery.com/jquery-1.9.1.min.js\"></script>`\r\n `<script src=\"http://eloone.github.io/jgridder/jgridder.js\"></script>`\r\n \r\nThe css :\r\n\r\n`<link href=\"https://raw.github.com/eloone/jgridder/master/css/grid.css\" rel=\"stylesheet\"></link>`\r\n\r\nTake example on the 'test' folder of this repository. \r\nOr directly view source on <http://eloone.net/jgridder/test> for a straightforward implementation.\r\n\r\n## Usage\r\nOnce you have followed the <a href=\"#requirements\">requirements</a>, \r\nyou can put this in your javascript file to implement the UI component :\r\n\r\nSimple implementation :\r\n\r\n```js\r\n//This will just draw the grid\r\n    var grid = new Grid({\r\n          width : 85,\r\n          height : 200,\r\n          border : 1,\r\n          nb_items : 47\r\n      });\r\n\r\n      //When the grid is finally pre-computed and ready we add it to the dom\r\n      $('body').append(grid.node);\r\n```             \r\n\r\n## Example\r\n\r\nExample with a click event on each box :\r\n\r\n```js\r\n      var totalItems = 47,\r\n      grid = new Grid({\r\n           width : 85,\r\n          height : 200,\r\n          border : 1,\r\n          nb_items : totalItems\r\n      });\r\n     \r\n      //Click handler when a box is clicked\r\n      function onClick(){    \r\n          alert('click on a box');\r\n      }\r\n      \r\n      //Adding a click event on each box\r\n      for(var j = 0; j < grid.items.length; j++){\r\n          grid.items[j].node.on('click', $.proxy(onClick, grid.items[j]));\r\n      }\r\n\r\n      //When the grid is finally pre-computed and ready we add it to the dom\r\n      $('body').append(grid.node);\r\n```\r\n## Structure\r\n\r\nThis script only takes care of generating the grid. \r\n\r\nIf you need to interact with the elements in the grid use the object that it returns :\r\n\r\n```js\r\nvar grid = new Grid({\r\n          width : 85,\r\n          height : 200,\r\n          border : 1,\r\n          nb_items : 47\r\n      });\r\n```\r\nwill return an object of this structure :\r\n\r\n```js\r\n{\r\n  node : '[object]', //the jquery node for the grid container => $('.grid')\r\n  items : [ //array of all the boxes in the grid\r\n   ...\r\n    {\r\n      node : '[object]', //jquery node for a box in the grid, => $('.box')\r\n      index : '[int]' //index of the box in the grid\r\n    },\r\n    {\r\n      node : '[object]', //jquery node for a box in the grid,\r\n      index : '[int]' //index of the box in the grid\r\n    }\r\n    ...\r\n  ]\r\n}\r\n```\r\n\r\nand an html of this structure :\r\n\r\n```html\r\n<div class=\"grid\">\r\n  ...\r\n  <ul class=\"row\">\r\n    <li class=\"box\"></li>\r\n    <li class=\"box\"></li>\r\n    <li class=\"box\"></li>\r\n  </ul>\r\n  <ul class=\"row\">\r\n    <li class=\"box\"></li>\r\n    <li class=\"box\"></li>\r\n    <li class=\"box\"></li>\r\n  </ul>\r\n  ...\r\n</div>\r\n\r\n```\r\n## Beyond the code\r\nhttp://machinesaredigging.com/2013/05/21/jgridder-how-to-fit-elements-in-a-sized-grid/\r\n\r\n## License\r\n\r\nBSD-style. See the LICENSE file.\r\n","google":"","note":"Don't delete this file! It's used internally to help with page regeneration."}